clairclient/__init__.py
clairclient/api_client.py
clairclient/configuration.py
clairclient/rest.py
clairclient/api/__init__.py
clairclient/api/ancestry_service_api.py
clairclient/api/notification_service_api.py
clairclient/models/__init__.py
clairclient/models/clairpb_ancestry.py
clairclient/models/clairpb_clair_status.py
clairclient/models/clairpb_feature.py
clairclient/models/clairpb_get_ancestry_response.py
clairclient/models/clairpb_get_notification_response.py
clairclient/models/clairpb_indexed_ancestry_name.py
clairclient/models/clairpb_layer.py
clairclient/models/clairpb_notification.py
clairclient/models/clairpb_paged_vulnerable_ancestries.py
clairclient/models/clairpb_post_ancestry_request.py
clairclient/models/clairpb_post_ancestry_response.py
clairclient/models/clairpb_vulnerability.py
clairclient/models/post_ancestry_request_post_layer.py
clairclient/models/protobuf_empty.py
clairclient-1.0.0.dist-info/METADATA
clairclient-1.0.0.dist-info/RECORD
clairclient-1.0.0.dist-info/WHEEL
clairclient-1.0.0.dist-info/top_level.txt
test/__init__.py
test/test_ancestry_service_api.py
test/test_clairpb_ancestry.py
test/test_clairpb_clair_status.py
test/test_clairpb_feature.py
test/test_clairpb_get_ancestry_response.py
test/test_clairpb_get_notification_response.py
test/test_clairpb_indexed_ancestry_name.py
test/test_clairpb_layer.py
test/test_clairpb_notification.py
test/test_clairpb_paged_vulnerable_ancestries.py
test/test_clairpb_post_ancestry_request.py
test/test_clairpb_post_ancestry_response.py
test/test_clairpb_vulnerability.py
test/test_notification_service_api.py
test/test_post_ancestry_request_post_layer.py
test/test_protobuf_empty.py
